morse3.py
morse3-0.47.dist-info/METADATA
morse3-0.47.dist-info/WHEEL
morse3-0.47.dist-info/top_level.txt
morse3-0.47.dist-info/RECORD
