Metadata-Version: 2.1
Name: morse3
Version: 0.47
Summary: A morse code encryption / decryption library
Home-page: https://github.com/Aayush9029/encodeDecode
Author: Aayush Pokharel
Author-email: aayushpokharel36@gmail.com
License: UNKNOWN
Platform: UNKNOWN
Classifier: Programming Language :: Python :: 3
Classifier: License :: OSI Approved :: MIT License
Classifier: Operating System :: OS Independent
